csvms/__init__.py
csvms/catalog.py
csvms/engine.py
csvms/exceptions.py
csvms/index.py
csvms/schema.py
csvms/table.py
csvms-0.2.14.dist-info/LICENSE
csvms-0.2.14.dist-info/WHEEL
csvms-0.2.14.dist-info/METADATA
csvms-0.2.14.dist-info/RECORD
