Metadata-Version: 2.1
Name: csvms
Version: 0.2.14
Summary: Comma-separated values management system
Home-page: https://didone.github.io/csvms/
License: MIT
Keywords: bootcamp,csv,dbms,database,relational-algebra
Author: Didone
Author-email: tiago.didone@compasso.com.br
Requires-Python: >=3.8,<4.0
Classifier: License :: OSI Approved :: MIT License
Classifier: Programming Language :: Python :: 3
Classifier: Programming Language :: Python :: 3.10
Classifier: Programming Language :: Python :: 3.8
Classifier: Programming Language :: Python :: 3.9
Classifier: Topic :: Database
Classifier: Topic :: Software Development :: Build Tools
Classifier: Topic :: Software Development :: Libraries :: Python Modules
Provides-Extra: bootcamp
Requires-Dist: docopt (>=0.6.2,<0.7.0); extra == "bootcamp"
Requires-Dist: ipykernel (>=6.15.0,<7.0.0); extra == "bootcamp"
Requires-Dist: mo-sql-parsing (>=8.185.22160,<9.0.0); extra == "bootcamp"
Project-URL: Repository, https://github.com/Didone/csvms.git
